setup.cfg
setup.py
solidus/OSXLocations.txt
solidus/Solidus.py
solidus/SolidusConfigFile.py
solidus/SolidusConfigFile.pyc
solidus/SolidusErrorLog.py
solidus/SolidusErrorLog.pyc
solidus/SolidusXMLLog.py
solidus/SolidusXMLLog.pyc
solidus/__init__.py
solidus/solidus.plist
solidus.egg-info/.DS_Store
solidus.egg-info/PKG-INFO
solidus.egg-info/SOURCES.txt
solidus.egg-info/dependency_links.txt
solidus.egg-info/not-zip-safe
solidus.egg-info/top_level.txt