Metadata-Version: 1.0
Name: solidus
Version: 0.10.3
Summary: Solidus Security Agent for OSX
Home-page: http://github.com/SolidusSecurity/SolidusOSX
Author: Joe Kovacic
Author-email: j.kovacic@SolidusSecurity.com
License: UNKNOWN
Platform: UNKNOWN
